{
  "_class": "symbolMaster",
  "allowsOverrides": true,
  "backgroundColor": {
    "_class": "color",
    "alpha": 1,
    "blue": 0.1176470588235294,
    "green": 0.1176470588235294,
    "red": 0.1176470588235294
  },
  "booleanOperation": -1,
  "clippingMaskMode": 0,
  "do_objectID": "2F74EE20-317D-417A-8E50-13C5745FBF10",
  "exportOptions": {
    "_class": "exportOptions",
    "exportFormats": [
    ],
    "includedLayerIds": [
    ],
    "layerOptions": 0,
    "shouldTrim": false
  },
  "frame": {
    "_class": "rect",
    "constrainProportions": false,
    "height": 154,
    "width": 1440,
    "x": 29254,
    "y": 3525
  },
  "groupLayout": {
    "_class": "MSImmutableFreeformGroupLayout"
  },
  "hasBackgroundColor": true,
  "hasClickThrough": true,
  "hasClippingMask": false,
  "horizontalRulerData": {
    "_class": "rulerData",
    "base": 0,
    "guides": [
    ]
  },
  "includeBackgroundColorInExport": true,
  "includeBackgroundColorInInstance": true,
  "includeInCloudUpload": true,
  "isFixedToViewport": false,
  "isFlippedHorizontal": false,
  "isFlippedVertical": false,
  "isFlowHome": false,
  "isLocked": false,
  "isVisible": true,
  "layerListExpandedType": 1,
  "layers": [
    {
      "class": "group",
      "id": "8164AD68-8849-4AA0-ABD9-4984E2240ABB"
    },
    {
      "class": "text",
      "id": "DCE71150-77AB-4C1A-8C79-012EFA862D01"
    },
    {
      "class": "symbolInstance",
      "id": "FC0DE83D-66CB-42D2-8636-72A1BEFDE727"
    }
  ],
  "layout": {
    "_class": "layoutGrid",
    "columnWidth": 78,
    "drawHorizontal": false,
    "drawHorizontalLines": false,
    "drawVertical": true,
    "gutterHeight": 12,
    "gutterWidth": 24,
    "guttersOutside": false,
    "horizontalOffset": 120.5,
    "isEnabled": true,
    "numberOfColumns": 12,
    "rowHeightMultiplication": 5,
    "totalWidth": 1200
  },
  "name": "02 Composants/Pied de page/Thème sombre/_items/Desktop/Partenaires secondaires",
  "nameIsFixed": true,
  "overrideProperties": [
    {
      "_class": "MSImmutableOverrideProperty",
      "canOverride": false,
      "overrideName": "FC0DE83D-66CB-42D2-8636-72A1BEFDE727/7356C27A-41FF-4D18-85BC-DD712B336487/D609DFA0-ACAF-4D21-96AD-3FB6BC1D6C43_layerStyle"
    },
    {
      "_class": "MSImmutableOverrideProperty",
      "canOverride": true,
      "overrideName": "649B4151-4935-484D-A5CD-5E311EE15502_symbolID"
    },
    {
      "_class": "MSImmutableOverrideProperty",
      "canOverride": true,
      "overrideName": "77F2D8D4-06FC-482A-BA46-6B6DF7F662E6_symbolID"
    },
    {
      "_class": "MSImmutableOverrideProperty",
      "canOverride": true,
      "overrideName": "95BB3109-8F75-4AD1-8E0C-0EDB1321A499_symbolID"
    },
    {
      "_class": "MSImmutableOverrideProperty",
      "canOverride": false,
      "overrideName": "FC0DE83D-66CB-42D2-8636-72A1BEFDE727/7356C27A-41FF-4D18-85BC-DD712B336487_symbolID"
    },
    {
      "_class": "MSImmutableOverrideProperty",
      "canOverride": false,
      "overrideName": "FC0DE83D-66CB-42D2-8636-72A1BEFDE727_symbolID"
    },
    {
      "_class": "MSImmutableOverrideProperty",
      "canOverride": false,
      "overrideName": "DCE71150-77AB-4C1A-8C79-012EFA862D01_textStyle"
    },
    {
      "_class": "MSImmutableOverrideProperty",
      "canOverride": false,
      "overrideName": "FC0DE83D-66CB-42D2-8636-72A1BEFDE727/7356C27A-41FF-4D18-85BC-DD712B336487/529E8FEE-0AF7-4925-9717-48DC625C5C30_layerStyle"
    },
    {
      "_class": "MSImmutableOverrideProperty",
      "canOverride": false,
      "overrideName": "FC0DE83D-66CB-42D2-8636-72A1BEFDE727/7356C27A-41FF-4D18-85BC-DD712B336487/07FB2E7B-F332-43BD-8EDF-92C381E91EFD_layerStyle"
    },
    {
      "_class": "MSImmutableOverrideProperty",
      "canOverride": true,
      "overrideName": "DCE71150-77AB-4C1A-8C79-012EFA862D01_stringValue"
    }
  ],
  "presetDictionary": {
  },
  "resizesContent": true,
  "resizingConstraint": 63,
  "resizingType": 0,
  "rotation": 0,
  "shouldBreakMaskChain": true,
  "style": {
    "_class": "style",
    "blur": {
      "_class": "blur",
      "center": "{0.5, 0.5}",
      "isEnabled": false,
      "motionAngle": 0,
      "radius": 10,
      "saturation": 1,
      "type": 0
    },
    "borderOptions": {
      "_class": "borderOptions",
      "dashPattern": [
      ],
      "isEnabled": true,
      "lineCapStyle": 0,
      "lineJoinStyle": 0
    },
    "borders": [
    ],
    "colorControls": {
      "_class": "colorControls",
      "brightness": 0,
      "contrast": 1,
      "hue": 0,
      "isEnabled": false,
      "saturation": 1
    },
    "contextSettings": {
      "_class": "graphicsContextSettings",
      "blendMode": 0,
      "opacity": 1
    },
    "do_objectID": "F96B75DB-62F5-4C3C-88CC-2DB95959472D",
    "endMarkerType": 0,
    "fills": [
    ],
    "innerShadows": [
    ],
    "miterLimit": 10,
    "shadows": [
    ],
    "startMarkerType": 0,
    "windingRule": 1
  },
  "symbolID": "E891FD20-B01E-4EEF-A79B-4AF5734AEEC2",
  "verticalRulerData": {
    "_class": "rulerData",
    "base": 0,
    "guides": [
    ]
  }
}