{
  "_class": "symbolMaster",
  "allowsOverrides": true,
  "backgroundColor": {
    "_class": "color",
    "alpha": 1,
    "blue": 0.1647058823529412,
    "green": 0.1647058823529412,
    "red": 0.1647058823529412
  },
  "booleanOperation": -1,
  "clippingMaskMode": 0,
  "do_objectID": "DB65055A-6434-48DC-956E-40120B3685EC",
  "exportOptions": {
    "_class": "exportOptions",
    "exportFormats": [
    ],
    "includedLayerIds": [
    ],
    "layerOptions": 0,
    "shouldTrim": false
  },
  "frame": {
    "_class": "rect",
    "constrainProportions": false,
    "height": 80,
    "width": 375,
    "x": 43196,
    "y": 947
  },
  "groupLayout": {
    "_class": "MSImmutableInferredGroupLayout",
    "axis": 1,
    "layoutAnchor": 0,
    "maxSize": 0,
    "minSize": 0
  },
  "hasBackgroundColor": true,
  "hasClickThrough": true,
  "hasClippingMask": false,
  "horizontalRulerData": {
    "_class": "rulerData",
    "base": 0,
    "guides": [
    ]
  },
  "includeBackgroundColorInExport": true,
  "includeBackgroundColorInInstance": false,
  "includeInCloudUpload": true,
  "isFixedToViewport": false,
  "isFlippedHorizontal": false,
  "isFlippedVertical": false,
  "isFlowHome": false,
  "isLocked": false,
  "isVisible": true,
  "layerListExpandedType": 1,
  "layers": [
    {
      "class": "text",
      "id": "B3E66FB1-9AE1-4C56-9A7F-1E68782CADB9"
    },
    {
      "class": "text",
      "id": "698C63E7-6F4E-4E9B-8C40-3D32A5D8DD69"
    }
  ],
  "name": "02 Composants/- Élements - ne pas utiliser/Tuiles/Thème sombre/contenu/Desktop/horizontale/titre + description",
  "nameIsFixed": true,
  "overrideProperties": [
    {
      "_class": "MSImmutableOverrideProperty",
      "canOverride": true,
      "overrideName": "B3E66FB1-9AE1-4C56-9A7F-1E68782CADB9_stringValue"
    },
    {
      "_class": "MSImmutableOverrideProperty",
      "canOverride": false,
      "overrideName": "698C63E7-6F4E-4E9B-8C40-3D32A5D8DD69_textStyle"
    },
    {
      "_class": "MSImmutableOverrideProperty",
      "canOverride": true,
      "overrideName": "698C63E7-6F4E-4E9B-8C40-3D32A5D8DD69_stringValue"
    },
    {
      "_class": "MSImmutableOverrideProperty",
      "canOverride": false,
      "overrideName": "B3E66FB1-9AE1-4C56-9A7F-1E68782CADB9_textStyle"
    }
  ],
  "presetDictionary": {
  },
  "resizesContent": false,
  "resizingConstraint": 63,
  "resizingType": 0,
  "rotation": 0,
  "shouldBreakMaskChain": true,
  "style": {
    "_class": "style",
    "blur": {
      "_class": "blur",
      "center": "{0.5, 0.5}",
      "isEnabled": false,
      "motionAngle": 0,
      "radius": 10,
      "saturation": 1,
      "type": 0
    },
    "borderOptions": {
      "_class": "borderOptions",
      "dashPattern": [
      ],
      "isEnabled": true,
      "lineCapStyle": 0,
      "lineJoinStyle": 0
    },
    "borders": [
    ],
    "colorControls": {
      "_class": "colorControls",
      "brightness": 0,
      "contrast": 1,
      "hue": 0,
      "isEnabled": false,
      "saturation": 1
    },
    "contextSettings": {
      "_class": "graphicsContextSettings",
      "blendMode": 0,
      "opacity": 1
    },
    "do_objectID": "6493857E-D9DF-40BF-8DAB-B9042F81AC53",
    "endMarkerType": 0,
    "fills": [
    ],
    "innerShadows": [
    ],
    "miterLimit": 10,
    "shadows": [
    ],
    "startMarkerType": 0,
    "windingRule": 1
  },
  "symbolID": "64ACB294-8AD2-4D5A-8066-40A27949397A",
  "verticalRulerData": {
    "_class": "rulerData",
    "base": 0,
    "guides": [
      1880,
      1884,
      -710,
      -710,
      -685
    ]
  }
}