{
  "_class": "symbolMaster",
  "allowsOverrides": true,
  "backgroundColor": {
    "_class": "color",
    "alpha": 1,
    "blue": 0.1647058823529412,
    "green": 0.1647058823529412,
    "red": 0.1647058823529412
  },
  "booleanOperation": -1,
  "clippingMaskMode": 0,
  "do_objectID": "E257E8CF-3F40-499D-AECD-5F98560EC2E8",
  "exportOptions": {
    "_class": "exportOptions",
    "exportFormats": [
    ],
    "includedLayerIds": [
    ],
    "layerOptions": 0,
    "shouldTrim": false
  },
  "frame": {
    "_class": "rect",
    "constrainProportions": false,
    "height": 72,
    "width": 288,
    "x": 22311,
    "y": 3355
  },
  "groupLayout": {
    "_class": "MSImmutableInferredGroupLayout",
    "axis": 1,
    "layoutAnchor": 0,
    "maxSize": 0,
    "minSize": 0
  },
  "hasBackgroundColor": true,
  "hasClickThrough": true,
  "hasClippingMask": false,
  "horizontalRulerData": {
    "_class": "rulerData",
    "base": 0,
    "guides": [
    ]
  },
  "includeBackgroundColorInExport": false,
  "includeBackgroundColorInInstance": true,
  "includeInCloudUpload": true,
  "isFixedToViewport": false,
  "isFlippedHorizontal": false,
  "isFlippedVertical": false,
  "isFlowHome": false,
  "isLocked": false,
  "isVisible": true,
  "layerListExpandedType": 1,
  "layers": [
    {
      "class": "rectangle",
      "id": "C7722667-6CAC-416E-8881-80ED25E61A82"
    },
    {
      "class": "text",
      "id": "DC88F17A-59BA-4AF7-A42D-4687B8D7A964"
    },
    {
      "class": "symbolInstance",
      "id": "7E3508D6-7801-48E9-A757-275C5233EC2D"
    }
  ],
  "name": "02 Composants/Navigation principale/Thème sombre/Mobile/_items/niveau 2/dernier lien-Défaut",
  "nameIsFixed": true,
  "overrideProperties": [
    {
      "_class": "MSImmutableOverrideProperty",
      "canOverride": false,
      "overrideName": "7E3508D6-7801-48E9-A757-275C5233EC2D/7356C27A-41FF-4D18-85BC-DD712B336487_symbolID"
    },
    {
      "_class": "MSImmutableOverrideProperty",
      "canOverride": true,
      "overrideName": "DC88F17A-59BA-4AF7-A42D-4687B8D7A964_stringValue"
    },
    {
      "_class": "MSImmutableOverrideProperty",
      "canOverride": false,
      "overrideName": "7E3508D6-7801-48E9-A757-275C5233EC2D/7356C27A-41FF-4D18-85BC-DD712B336487/07FB2E7B-F332-43BD-8EDF-92C381E91EFD_layerStyle"
    },
    {
      "_class": "MSImmutableOverrideProperty",
      "canOverride": false,
      "overrideName": "7E3508D6-7801-48E9-A757-275C5233EC2D/7356C27A-41FF-4D18-85BC-DD712B336487/D609DFA0-ACAF-4D21-96AD-3FB6BC1D6C43_layerStyle"
    },
    {
      "_class": "MSImmutableOverrideProperty",
      "canOverride": false,
      "overrideName": "7E3508D6-7801-48E9-A757-275C5233EC2D/7356C27A-41FF-4D18-85BC-DD712B336487/529E8FEE-0AF7-4925-9717-48DC625C5C30_layerStyle"
    },
    {
      "_class": "MSImmutableOverrideProperty",
      "canOverride": true,
      "overrideName": "7E3508D6-7801-48E9-A757-275C5233EC2D_symbolID"
    },
    {
      "_class": "MSImmutableOverrideProperty",
      "canOverride": false,
      "overrideName": "DC88F17A-59BA-4AF7-A42D-4687B8D7A964_textStyle"
    }
  ],
  "presetDictionary": {
  },
  "resizesContent": false,
  "resizingConstraint": 63,
  "resizingType": 0,
  "rotation": 0,
  "shouldBreakMaskChain": true,
  "style": {
    "_class": "style",
    "blur": {
      "_class": "blur",
      "center": "{0.5, 0.5}",
      "isEnabled": false,
      "motionAngle": 0,
      "radius": 10,
      "saturation": 1,
      "type": 0
    },
    "borderOptions": {
      "_class": "borderOptions",
      "dashPattern": [
      ],
      "isEnabled": true,
      "lineCapStyle": 0,
      "lineJoinStyle": 0
    },
    "borders": [
    ],
    "colorControls": {
      "_class": "colorControls",
      "brightness": 0,
      "contrast": 1,
      "hue": 0,
      "isEnabled": false,
      "saturation": 1
    },
    "contextSettings": {
      "_class": "graphicsContextSettings",
      "blendMode": 0,
      "opacity": 1
    },
    "do_objectID": "31D30E10-3644-40F5-AAC7-E41DE94ADD50",
    "endMarkerType": 0,
    "fills": [
    ],
    "innerShadows": [
    ],
    "miterLimit": 10,
    "shadows": [
    ],
    "startMarkerType": 0,
    "windingRule": 1
  },
  "symbolID": "5F18127B-CAC9-4028-8C25-A4A0F2148BA3",
  "verticalRulerData": {
    "_class": "rulerData",
    "base": 0,
    "guides": [
    ]
  }
}