{
  "_class": "group",
  "booleanOperation": -1,
  "clippingMaskMode": 0,
  "do_objectID": "C2A39AAE-AF68-4AFA-A046-F3EF7097C751",
  "exportOptions": {
    "_class": "exportOptions",
    "exportFormats": [
    ],
    "includedLayerIds": [
    ],
    "layerOptions": 0,
    "shouldTrim": false
  },
  "frame": {
    "_class": "rect",
    "constrainProportions": false,
    "height": 273,
    "width": 162,
    "x": 970,
    "y": 77
  },
  "groupLayout": {
    "_class": "MSImmutableFreeformGroupLayout"
  },
  "hasClickThrough": false,
  "hasClippingMask": false,
  "isFixedToViewport": false,
  "isFlippedHorizontal": false,
  "isFlippedVertical": false,
  "isLocked": false,
  "isVisible": true,
  "layerListExpandedType": 0,
  "layers": [
    {
      "class": "rectangle",
      "id": "230A1C9E-9A02-4D88-BF67-2E8C4881FA6B"
    },
    {
      "class": "rectangle",
      "id": "85900575-5849-467B-B3C9-CA79CAC1A3E6"
    },
    {
      "class": "group",
      "id": "7EDF83A6-9BCD-4913-BD6F-B774BDAA4513"
    },
    {
      "class": "group",
      "id": "52204B66-954C-4F9D-B475-C58F5C3623B4"
    },
    {
      "class": "text",
      "id": "96B82081-CEA2-4A2C-85A0-86185D2E176B"
    },
    {
      "class": "text",
      "id": "DEF617C9-BB90-4BF0-A15C-C6B3021ADB49"
    }
  ],
  "name": "F- $blue-soft",
  "nameIsFixed": true,
  "resizingConstraint": 63,
  "resizingType": 0,
  "rotation": 0,
  "shouldBreakMaskChain": false,
  "style": {
    "_class": "style",
    "blur": {
      "_class": "blur",
      "center": "{0.5, 0.5}",
      "isEnabled": false,
      "motionAngle": 0,
      "radius": 10,
      "saturation": 1,
      "type": 0
    },
    "borderOptions": {
      "_class": "borderOptions",
      "dashPattern": [
      ],
      "isEnabled": true,
      "lineCapStyle": 0,
      "lineJoinStyle": 0
    },
    "borders": [
    ],
    "colorControls": {
      "_class": "colorControls",
      "brightness": 0,
      "contrast": 1,
      "hue": 0,
      "isEnabled": false,
      "saturation": 1
    },
    "contextSettings": {
      "_class": "graphicsContextSettings",
      "blendMode": 0,
      "opacity": 1
    },
    "do_objectID": "FE3B2A9F-0826-42C9-B082-CD89C09676B7",
    "endMarkerType": 0,
    "fills": [
    ],
    "innerShadows": [
    ],
    "miterLimit": 10,
    "shadows": [
    ],
    "startMarkerType": 0,
    "windingRule": 1
  }
}