{
  "_class": "symbolMaster",
  "allowsOverrides": true,
  "backgroundColor": {
    "_class": "color",
    "alpha": 1,
    "blue": 1,
    "green": 1,
    "red": 1
  },
  "booleanOperation": -1,
  "clippingMaskMode": 0,
  "do_objectID": "ED8D7F32-2E15-403F-9642-2ECCAB96EBE4",
  "exportOptions": {
    "_class": "exportOptions",
    "exportFormats": [
    ],
    "includedLayerIds": [
    ],
    "layerOptions": 0,
    "shouldTrim": false
  },
  "frame": {
    "_class": "rect",
    "constrainProportions": false,
    "height": 408,
    "width": 792,
    "x": 61159,
    "y": 768
  },
  "groupLayout": {
    "_class": "MSImmutableInferredGroupLayout",
    "axis": 1,
    "layoutAnchor": 0,
    "maxSize": 0,
    "minSize": 0
  },
  "hasBackgroundColor": false,
  "hasClickThrough": true,
  "hasClippingMask": false,
  "horizontalRulerData": {
    "_class": "rulerData",
    "base": 0,
    "guides": [
    ]
  },
  "includeBackgroundColorInExport": true,
  "includeBackgroundColorInInstance": false,
  "includeInCloudUpload": true,
  "isFixedToViewport": false,
  "isFlippedHorizontal": false,
  "isFlippedVertical": false,
  "isFlowHome": false,
  "isLocked": false,
  "isVisible": true,
  "layerListExpandedType": 1,
  "layers": [
    {
      "class": "symbolInstance",
      "id": "6E207DA6-1792-4573-910F-05606D4E7515"
    },
    {
      "class": "group",
      "id": "883E8F68-18AF-457D-877E-4C000456E73E"
    },
    {
      "class": "text",
      "id": "62A0CF90-323F-4F8E-8C6B-269A37F4036F"
    },
    {
      "class": "group",
      "id": "E4CDDACA-2888-418B-9CBD-A334AD18DEE5"
    },
    {
      "class": "symbolInstance",
      "id": "F2B771EC-1F50-4F35-92D2-81DB018FF6F0"
    }
  ],
  "name": "02 Composants/Modale/Thème clair/Desktop/Défaut/Avec zone action/Défaut/LG",
  "nameIsFixed": false,
  "overrideProperties": [
    {
      "_class": "MSImmutableOverrideProperty",
      "canOverride": false,
      "overrideName": "62A0CF90-323F-4F8E-8C6B-269A37F4036F_textStyle"
    },
    {
      "_class": "MSImmutableOverrideProperty",
      "canOverride": true,
      "overrideName": "7EBEEB86-F182-4C4B-AEF7-5F991DAB9E13_symbolID"
    },
    {
      "_class": "MSImmutableOverrideProperty",
      "canOverride": true,
      "overrideName": "4F8A2137-44FE-4964-87A4-031C8DA16D55_symbolID"
    },
    {
      "_class": "MSImmutableOverrideProperty",
      "canOverride": false,
      "overrideName": "23B98DFB-1308-4385-9C0A-FE81671C5AEA_layerStyle"
    },
    {
      "_class": "MSImmutableOverrideProperty",
      "canOverride": true,
      "overrideName": "573676A8-6FFC-4F14-8EAD-67884E6D5EE7_symbolID"
    },
    {
      "_class": "MSImmutableOverrideProperty",
      "canOverride": true,
      "overrideName": "62A0CF90-323F-4F8E-8C6B-269A37F4036F_stringValue"
    },
    {
      "_class": "MSImmutableOverrideProperty",
      "canOverride": false,
      "overrideName": "6E207DA6-1792-4573-910F-05606D4E7515_symbolID"
    },
    {
      "_class": "MSImmutableOverrideProperty",
      "canOverride": true,
      "overrideName": "DDB6022F-96F7-43B4-8E9B-375AD22E56D0_stringValue"
    },
    {
      "_class": "MSImmutableOverrideProperty",
      "canOverride": false,
      "overrideName": "573676A8-6FFC-4F14-8EAD-67884E6D5EE7/9EBF97A4-93EB-4A18-BCD0-E0CC6BC7FB02/EAA2646E-470D-4785-862E-F3A964661D6D_layerStyle"
    },
    {
      "_class": "MSImmutableOverrideProperty",
      "canOverride": false,
      "overrideName": "DDB6022F-96F7-43B4-8E9B-375AD22E56D0_textStyle"
    },
    {
      "_class": "MSImmutableOverrideProperty",
      "canOverride": false,
      "overrideName": "6E207DA6-1792-4573-910F-05606D4E7515/07FB2E7B-F332-43BD-8EDF-92C381E91EFD_layerStyle"
    },
    {
      "_class": "MSImmutableOverrideProperty",
      "canOverride": false,
      "overrideName": "F2B771EC-1F50-4F35-92D2-81DB018FF6F0_symbolID"
    },
    {
      "_class": "MSImmutableOverrideProperty",
      "canOverride": false,
      "overrideName": "6E207DA6-1792-4573-910F-05606D4E7515/D609DFA0-ACAF-4D21-96AD-3FB6BC1D6C43_layerStyle"
    },
    {
      "_class": "MSImmutableOverrideProperty",
      "canOverride": false,
      "overrideName": "6E207DA6-1792-4573-910F-05606D4E7515/529E8FEE-0AF7-4925-9717-48DC625C5C30_layerStyle"
    },
    {
      "_class": "MSImmutableOverrideProperty",
      "canOverride": true,
      "overrideName": "573676A8-6FFC-4F14-8EAD-67884E6D5EE7/9EBF97A4-93EB-4A18-BCD0-E0CC6BC7FB02_symbolID"
    }
  ],
  "presetDictionary": {
  },
  "resizesContent": false,
  "resizingConstraint": 63,
  "resizingType": 0,
  "rotation": 0,
  "shouldBreakMaskChain": true,
  "style": {
    "_class": "style",
    "blur": {
      "_class": "blur",
      "center": "{0.5, 0.5}",
      "isEnabled": false,
      "motionAngle": 0,
      "radius": 10,
      "saturation": 1,
      "type": 0
    },
    "borderOptions": {
      "_class": "borderOptions",
      "dashPattern": [
      ],
      "isEnabled": true,
      "lineCapStyle": 0,
      "lineJoinStyle": 0
    },
    "borders": [
    ],
    "colorControls": {
      "_class": "colorControls",
      "brightness": 0,
      "contrast": 1,
      "hue": 0,
      "isEnabled": false,
      "saturation": 1
    },
    "contextSettings": {
      "_class": "graphicsContextSettings",
      "blendMode": 0,
      "opacity": 1
    },
    "do_objectID": "9F2D4559-42A8-4E5C-ACCD-BE12DC109586",
    "endMarkerType": 0,
    "fills": [
    ],
    "innerShadows": [
    ],
    "miterLimit": 10,
    "shadows": [
    ],
    "startMarkerType": 0,
    "windingRule": 1
  },
  "symbolID": "BA898D6E-9C4E-4C1A-ACFB-41EF847E0A1B",
  "verticalRulerData": {
    "_class": "rulerData",
    "base": 0,
    "guides": [
    ]
  }
}