{
  "_class": "symbolMaster",
  "allowsOverrides": true,
  "backgroundColor": {
    "_class": "color",
    "alpha": 1,
    "blue": 1,
    "green": 1,
    "red": 1
  },
  "booleanOperation": -1,
  "clippingMaskMode": 0,
  "do_objectID": "0788C5BC-163A-41E8-BF44-E6A3AFED16C0",
  "exportOptions": {
    "_class": "exportOptions",
    "exportFormats": [
    ],
    "includedLayerIds": [
    ],
    "layerOptions": 0,
    "shouldTrim": false
  },
  "frame": {
    "_class": "rect",
    "constrainProportions": false,
    "height": 392,
    "width": 792,
    "x": 57166,
    "y": 839
  },
  "groupLayout": {
    "_class": "MSImmutableInferredGroupLayout",
    "axis": 1,
    "layoutAnchor": 0,
    "maxSize": 0,
    "minSize": 0
  },
  "hasBackgroundColor": false,
  "hasClickThrough": true,
  "hasClippingMask": false,
  "horizontalRulerData": {
    "_class": "rulerData",
    "base": 0,
    "guides": [
    ]
  },
  "includeBackgroundColorInExport": true,
  "includeBackgroundColorInInstance": false,
  "includeInCloudUpload": true,
  "isFixedToViewport": false,
  "isFlippedHorizontal": false,
  "isFlippedVertical": false,
  "isFlowHome": false,
  "isLocked": false,
  "isVisible": true,
  "layerListExpandedType": 1,
  "layers": [
    {
      "class": "symbolInstance",
      "id": "A513EAB8-28B2-4A94-A2EC-22CE89D9FA7D"
    },
    {
      "class": "symbolInstance",
      "id": "408F1517-1F00-4929-AE7E-4E056CC0BDA9"
    },
    {
      "class": "symbolInstance",
      "id": "96358A39-2791-454B-A78E-C11E05A77959"
    },
    {
      "class": "symbolInstance",
      "id": "34B44824-59C4-43A6-8CF9-82ED0DF05243"
    },
    {
      "class": "symbolInstance",
      "id": "C96ED353-F1ED-4CBA-BAEF-6A026D7C3CAC"
    },
    {
      "class": "symbolInstance",
      "id": "C0345C30-8383-4AE0-9CFA-8AEAE8E95E29"
    },
    {
      "class": "symbolInstance",
      "id": "EE249EEB-C42D-4DB5-9C2A-ECC3D0A7574C"
    }
  ],
  "name": "02 Composants/Tableau/Thème clair/Desktop/Tableau max avec bordure",
  "nameIsFixed": true,
  "overrideProperties": [
    {
      "_class": "MSImmutableOverrideProperty",
      "canOverride": true,
      "overrideName": "96358A39-2791-454B-A78E-C11E05A77959_symbolID"
    },
    {
      "_class": "MSImmutableOverrideProperty",
      "canOverride": true,
      "overrideName": "C96ED353-F1ED-4CBA-BAEF-6A026D7C3CAC_symbolID"
    },
    {
      "_class": "MSImmutableOverrideProperty",
      "canOverride": true,
      "overrideName": "A513EAB8-28B2-4A94-A2EC-22CE89D9FA7D_symbolID"
    },
    {
      "_class": "MSImmutableOverrideProperty",
      "canOverride": true,
      "overrideName": "408F1517-1F00-4929-AE7E-4E056CC0BDA9_symbolID"
    },
    {
      "_class": "MSImmutableOverrideProperty",
      "canOverride": true,
      "overrideName": "C0345C30-8383-4AE0-9CFA-8AEAE8E95E29_symbolID"
    },
    {
      "_class": "MSImmutableOverrideProperty",
      "canOverride": true,
      "overrideName": "34B44824-59C4-43A6-8CF9-82ED0DF05243_symbolID"
    },
    {
      "_class": "MSImmutableOverrideProperty",
      "canOverride": true,
      "overrideName": "EE249EEB-C42D-4DB5-9C2A-ECC3D0A7574C_symbolID"
    }
  ],
  "presetDictionary": {
  },
  "resizesContent": false,
  "resizingConstraint": 63,
  "resizingType": 0,
  "rotation": 0,
  "shouldBreakMaskChain": true,
  "style": {
    "_class": "style",
    "blur": {
      "_class": "blur",
      "center": "{0.5, 0.5}",
      "isEnabled": false,
      "motionAngle": 0,
      "radius": 10,
      "saturation": 1,
      "type": 0
    },
    "borderOptions": {
      "_class": "borderOptions",
      "dashPattern": [
      ],
      "isEnabled": true,
      "lineCapStyle": 0,
      "lineJoinStyle": 0
    },
    "borders": [
    ],
    "colorControls": {
      "_class": "colorControls",
      "brightness": 0,
      "contrast": 1,
      "hue": 0,
      "isEnabled": false,
      "saturation": 1
    },
    "contextSettings": {
      "_class": "graphicsContextSettings",
      "blendMode": 0,
      "opacity": 1
    },
    "do_objectID": "5F049822-9D80-41A9-BAE9-7A387BC5933B",
    "endMarkerType": 0,
    "fills": [
    ],
    "innerShadows": [
    ],
    "miterLimit": 10,
    "shadows": [
    ],
    "startMarkerType": 0,
    "windingRule": 1
  },
  "symbolID": "A5098CE5-3578-42F1-9CF4-72E0BBBF9811",
  "verticalRulerData": {
    "_class": "rulerData",
    "base": 0,
    "guides": [
    ]
  }
}