{
  "_class": "symbolMaster",
  "allowsOverrides": true,
  "backgroundColor": {
    "_class": "color",
    "alpha": 1,
    "blue": 1,
    "green": 1,
    "red": 1
  },
  "booleanOperation": -1,
  "clippingMaskMode": 0,
  "do_objectID": "6E2FCA86-D140-48D9-8949-C5A0E35347BE",
  "exportOptions": {
    "_class": "exportOptions",
    "exportFormats": [
    ],
    "includedLayerIds": [
    ],
    "layerOptions": 0,
    "shouldTrim": false
  },
  "frame": {
    "_class": "rect",
    "constrainProportions": false,
    "height": 272,
    "width": 32,
    "x": 6917,
    "y": 4305
  },
  "groupLayout": {
    "_class": "MSImmutableInferredGroupLayout",
    "axis": 1,
    "layoutAnchor": 0,
    "maxSize": 0,
    "minSize": 0
  },
  "hasBackgroundColor": false,
  "hasClickThrough": true,
  "hasClippingMask": false,
  "horizontalRulerData": {
    "_class": "rulerData",
    "base": 0,
    "guides": [
    ]
  },
  "includeBackgroundColorInExport": true,
  "includeBackgroundColorInInstance": false,
  "includeInCloudUpload": true,
  "isFixedToViewport": false,
  "isFlippedHorizontal": false,
  "isFlippedVertical": false,
  "isFlowHome": false,
  "isLocked": false,
  "isVisible": true,
  "layerListExpandedType": 1,
  "layers": [
    {
      "class": "symbolInstance",
      "id": "10995405-B450-47CA-B752-76A0B5CBE810"
    },
    {
      "class": "symbolInstance",
      "id": "EB125CC8-14EF-4BFC-B0D6-DF8DF85604BC"
    },
    {
      "class": "symbolInstance",
      "id": "E95830DF-73F1-4696-A075-4284E46F958A"
    },
    {
      "class": "symbolInstance",
      "id": "AD53146B-2100-45AE-B635-1D53CFDE253C"
    },
    {
      "class": "symbolInstance",
      "id": "3D67F12C-A947-43AC-866F-31D4377EBD88"
    },
    {
      "class": "symbolInstance",
      "id": "B135900C-900E-4CAB-BCF1-12FDD3BAF7D3"
    }
  ],
  "name": "02 Composants/Groupe de boutons/Thème clair/Vertical/Non hierarchisé/SM",
  "nameIsFixed": true,
  "overrideProperties": [
    {
      "_class": "MSImmutableOverrideProperty",
      "canOverride": true,
      "overrideName": "3D67F12C-A947-43AC-866F-31D4377EBD88_symbolID"
    },
    {
      "_class": "MSImmutableOverrideProperty",
      "canOverride": true,
      "overrideName": "E95830DF-73F1-4696-A075-4284E46F958A_symbolID"
    },
    {
      "_class": "MSImmutableOverrideProperty",
      "canOverride": true,
      "overrideName": "AD53146B-2100-45AE-B635-1D53CFDE253C_symbolID"
    },
    {
      "_class": "MSImmutableOverrideProperty",
      "canOverride": true,
      "overrideName": "B135900C-900E-4CAB-BCF1-12FDD3BAF7D3_symbolID"
    },
    {
      "_class": "MSImmutableOverrideProperty",
      "canOverride": true,
      "overrideName": "10995405-B450-47CA-B752-76A0B5CBE810_symbolID"
    },
    {
      "_class": "MSImmutableOverrideProperty",
      "canOverride": true,
      "overrideName": "EB125CC8-14EF-4BFC-B0D6-DF8DF85604BC_symbolID"
    }
  ],
  "presetDictionary": {
  },
  "resizesContent": false,
  "resizingConstraint": 63,
  "resizingType": 0,
  "rotation": 0,
  "shouldBreakMaskChain": true,
  "style": {
    "_class": "style",
    "blur": {
      "_class": "blur",
      "center": "{0.5, 0.5}",
      "isEnabled": false,
      "motionAngle": 0,
      "radius": 10,
      "saturation": 1,
      "type": 0
    },
    "borderOptions": {
      "_class": "borderOptions",
      "dashPattern": [
      ],
      "isEnabled": true,
      "lineCapStyle": 0,
      "lineJoinStyle": 0
    },
    "borders": [
    ],
    "colorControls": {
      "_class": "colorControls",
      "brightness": 0,
      "contrast": 1,
      "hue": 0,
      "isEnabled": false,
      "saturation": 1
    },
    "contextSettings": {
      "_class": "graphicsContextSettings",
      "blendMode": 0,
      "opacity": 1
    },
    "do_objectID": "9823C10E-C437-49B5-B60C-FD0750AC3CA2",
    "endMarkerType": 0,
    "fills": [
    ],
    "innerShadows": [
    ],
    "miterLimit": 10,
    "shadows": [
    ],
    "startMarkerType": 0,
    "windingRule": 1
  },
  "symbolID": "C0D4866E-F5A2-4740-840E-959193409F43",
  "verticalRulerData": {
    "_class": "rulerData",
    "base": 0,
    "guides": [
    ]
  }
}