{
  "_class": "symbolMaster",
  "allowsOverrides": true,
  "backgroundColor": {
    "_class": "color",
    "alpha": 1,
    "blue": 0.1176470588235294,
    "green": 0.1176470588235294,
    "red": 0.1176470588235294
  },
  "booleanOperation": -1,
  "clippingMaskMode": 0,
  "do_objectID": "A1144A14-E7E6-4E10-9F0E-A92CBE998E82",
  "exportOptions": {
    "_class": "exportOptions",
    "exportFormats": [
    ],
    "includedLayerIds": [
    ],
    "layerOptions": 0,
    "shouldTrim": false
  },
  "frame": {
    "_class": "rect",
    "constrainProportions": false,
    "height": 196,
    "width": 298,
    "x": 8738,
    "y": 5859
  },
  "groupLayout": {
    "_class": "MSImmutableInferredGroupLayout",
    "axis": 1,
    "layoutAnchor": 0,
    "maxSize": 0,
    "minSize": 0
  },
  "hasBackgroundColor": true,
  "hasClickThrough": true,
  "hasClippingMask": false,
  "horizontalRulerData": {
    "_class": "rulerData",
    "base": 0,
    "guides": [
    ]
  },
  "includeBackgroundColorInExport": false,
  "includeBackgroundColorInInstance": false,
  "includeInCloudUpload": true,
  "isFixedToViewport": false,
  "isFlippedHorizontal": false,
  "isFlippedVertical": false,
  "isFlowHome": false,
  "isLocked": false,
  "isVisible": true,
  "layerListExpandedType": 1,
  "layers": [
    {
      "class": "group",
      "id": "EC822558-A19D-4C95-B65C-BE2EE4F67504"
    },
    {
      "class": "group",
      "id": "15031AD3-013D-4E61-AAA3-D9E29DEAF6D8"
    },
    {
      "class": "text",
      "id": "1C54A6D0-3E7E-4389-90B3-89EC7107FE3B"
    }
  ],
  "name": "02 Composants/Cases à cocher/Thème sombre/7) Groupe/Erreur",
  "nameIsFixed": true,
  "overrideProperties": [
    {
      "_class": "MSImmutableOverrideProperty",
      "canOverride": false,
      "overrideName": "404A7AB1-3EAE-40ED-9B1C-4D3F9E2042CA_symbolID"
    },
    {
      "_class": "MSImmutableOverrideProperty",
      "canOverride": false,
      "overrideName": "049CF4FF-938B-4E6A-9F44-CBFC3E37466D/C9038ACC-D833-4FC2-923F-E1B425AF9482_textStyle"
    },
    {
      "_class": "MSImmutableOverrideProperty",
      "canOverride": false,
      "overrideName": "2CDA7F6F-C1AD-4F34-AE89-9E9B565529C6/C9038ACC-D833-4FC2-923F-E1B425AF9482_textStyle"
    },
    {
      "_class": "MSImmutableOverrideProperty",
      "canOverride": false,
      "overrideName": "705FC8BC-19AE-4613-B4DA-80489EB45C29/C9038ACC-D833-4FC2-923F-E1B425AF9482_textStyle"
    },
    {
      "_class": "MSImmutableOverrideProperty",
      "canOverride": false,
      "overrideName": "404A7AB1-3EAE-40ED-9B1C-4D3F9E2042CA/BC201FA4-84CF-43C5-B09B-97223735EC12/33DF16F1-3205-43CA-9DD2-99F0BD297871_layerStyle"
    },
    {
      "_class": "MSImmutableOverrideProperty",
      "canOverride": false,
      "overrideName": "404A7AB1-3EAE-40ED-9B1C-4D3F9E2042CA/BC201FA4-84CF-43C5-B09B-97223735EC12_symbolID"
    },
    {
      "_class": "MSImmutableOverrideProperty",
      "canOverride": false,
      "overrideName": "5B20818D-67E6-4D78-8A6E-4087EAA5DC17_textStyle"
    },
    {
      "_class": "MSImmutableOverrideProperty",
      "canOverride": false,
      "overrideName": "1C54A6D0-3E7E-4389-90B3-89EC7107FE3B_textStyle"
    },
    {
      "_class": "MSImmutableOverrideProperty",
      "canOverride": true,
      "overrideName": "2CDA7F6F-C1AD-4F34-AE89-9E9B565529C6_symbolID"
    },
    {
      "_class": "MSImmutableOverrideProperty",
      "canOverride": true,
      "overrideName": "1C54A6D0-3E7E-4389-90B3-89EC7107FE3B_stringValue"
    },
    {
      "_class": "MSImmutableOverrideProperty",
      "canOverride": false,
      "overrideName": "705FC8BC-19AE-4613-B4DA-80489EB45C29/2B32D78E-BA71-4A23-B568-CB428D6F99DF_symbolID"
    },
    {
      "_class": "MSImmutableOverrideProperty",
      "canOverride": true,
      "overrideName": "5B20818D-67E6-4D78-8A6E-4087EAA5DC17_stringValue"
    },
    {
      "_class": "MSImmutableOverrideProperty",
      "canOverride": false,
      "overrideName": "0D939556-9EE2-49B9-8F19-B25669DFEEF4_layerStyle"
    },
    {
      "_class": "MSImmutableOverrideProperty",
      "canOverride": true,
      "overrideName": "705FC8BC-19AE-4613-B4DA-80489EB45C29_symbolID"
    },
    {
      "_class": "MSImmutableOverrideProperty",
      "canOverride": true,
      "overrideName": "049CF4FF-938B-4E6A-9F44-CBFC3E37466D_symbolID"
    },
    {
      "_class": "MSImmutableOverrideProperty",
      "canOverride": false,
      "overrideName": "2CDA7F6F-C1AD-4F34-AE89-9E9B565529C6/2B32D78E-BA71-4A23-B568-CB428D6F99DF/A9611B38-2FAC-4AE1-9310-C2FCCD3F053E_layerStyle"
    },
    {
      "_class": "MSImmutableOverrideProperty",
      "canOverride": false,
      "overrideName": "705FC8BC-19AE-4613-B4DA-80489EB45C29/2B32D78E-BA71-4A23-B568-CB428D6F99DF/A9611B38-2FAC-4AE1-9310-C2FCCD3F053E_layerStyle"
    },
    {
      "_class": "MSImmutableOverrideProperty",
      "canOverride": false,
      "overrideName": "049CF4FF-938B-4E6A-9F44-CBFC3E37466D/2B32D78E-BA71-4A23-B568-CB428D6F99DF/A9611B38-2FAC-4AE1-9310-C2FCCD3F053E_layerStyle"
    },
    {
      "_class": "MSImmutableOverrideProperty",
      "canOverride": false,
      "overrideName": "2CDA7F6F-C1AD-4F34-AE89-9E9B565529C6/2B32D78E-BA71-4A23-B568-CB428D6F99DF_symbolID"
    },
    {
      "_class": "MSImmutableOverrideProperty",
      "canOverride": false,
      "overrideName": "049CF4FF-938B-4E6A-9F44-CBFC3E37466D/2B32D78E-BA71-4A23-B568-CB428D6F99DF_symbolID"
    }
  ],
  "presetDictionary": {
  },
  "resizesContent": false,
  "resizingConstraint": 63,
  "resizingType": 0,
  "rotation": 0,
  "shouldBreakMaskChain": true,
  "style": {
    "_class": "style",
    "blur": {
      "_class": "blur",
      "center": "{0.5, 0.5}",
      "isEnabled": false,
      "motionAngle": 0,
      "radius": 10,
      "saturation": 1,
      "type": 0
    },
    "borderOptions": {
      "_class": "borderOptions",
      "dashPattern": [
      ],
      "isEnabled": true,
      "lineCapStyle": 0,
      "lineJoinStyle": 0
    },
    "borders": [
    ],
    "colorControls": {
      "_class": "colorControls",
      "brightness": 0,
      "contrast": 1,
      "hue": 0,
      "isEnabled": false,
      "saturation": 1
    },
    "contextSettings": {
      "_class": "graphicsContextSettings",
      "blendMode": 0,
      "opacity": 1
    },
    "do_objectID": "372E3283-C7D8-4BBD-AEBE-21F79E7218C9",
    "endMarkerType": 0,
    "fills": [
    ],
    "innerShadows": [
    ],
    "miterLimit": 10,
    "shadows": [
    ],
    "startMarkerType": 0,
    "windingRule": 1
  },
  "symbolID": "C61F8E09-3154-41FA-8FC8-431D5AEDA126",
  "verticalRulerData": {
    "_class": "rulerData",
    "base": 0,
    "guides": [
    ]
  }
}